cricketpy/__main__.py
cricketpy-1.1.3.dist-info/LICENSE
cricketpy-1.1.3.dist-info/METADATA
cricketpy-1.1.3.dist-info/WHEEL
cricketpy-1.1.3.dist-info/entry_points.txt
cricketpy-1.1.3.dist-info/top_level.txt
cricketpy-1.1.3.dist-info/RECORD
